{
  "items": [
    {
      "url": "/watch?v=wIqa9uVnXCQ",
      "title": "I Want To Break Free",
      "thumbnail": "https://pipedproxy.kavin.rocks/jRsNoO2SWEPNj9YpAAK_TpUx4izOiAl1XUBWwFDSNosxGj7c8SfsRYtL0n_5QOsGEEhjLG_01Pp-T9g=w120-h120-l90-rw?host=lh3.googleusercontent.com",
      "uploaderName": "Queen",
      "uploaderUrl": "/channel/UCEPMVbUzImPl4p8k4LkGevA",
      "uploaderAvatar": null,
      "uploadedDate": null,
      "shortDescription": null,
      "duration": 224,
      "views": -1,
      "uploaded": -1,
      "uploaderVerified": false
    },
    {
      "url": "/watch?v=3O0D6MvWFf4",
      "title": "The Show Must Go On",
      "thumbnail": "https://pipedproxy.kavin.rocks/kBrnnQZxMq9G4VCownBnQB3nmi0LrolZAG0a2c0-9Bt8BAFHPDafdQYdbZUJlaqVM1vjC3GWLJ3W1dtb=w120-h120-l90-rw?host=lh3.googleusercontent.com",
      "uploaderName": "Queen",
      "uploaderUrl": "/channel/UCEPMVbUzImPl4p8k4LkGevA",
      "uploaderAvatar": null,
      "uploadedDate": null,
      "shortDescription": null,
      "duration": 264,
      "views": -1,
      "uploaded": -1,
      "uploaderVerified": false
    },
    {
      "url": "/watch?v=8r3FaCiVFbA",
      "title": "I Want To Break Free (Single Remix)",
      "thumbnail": "https://pipedproxy.kavin.rocks/XI7kN3Ic4HmkQWj4M-DnOPttjfLvF4F1C3SUYeSNZ76xgUUe5gafl7KsRdnVY_n3nKzSNEVDOPDfq88=w120-h120-l90-rw?host=lh3.googleusercontent.com",
      "uploaderName": "Queen",
      "uploaderUrl": "/channel/UCEPMVbUzImPl4p8k4LkGevA",
      "uploaderAvatar": null,
      "uploadedDate": null,
      "shortDescription": null,
      "duration": 259,
      "views": -1,
      "uploaded": -1,
      "uploaderVerified": false
    },
    {
      "url": "/watch?v=2bqm4gRY3mA",
      "title": "Love Of My Life",
      "thumbnail": "https://pipedproxy.kavin.rocks/9CrMB2k2WFBUGXQXlaFfwP8e5_Q8FiUqQ8ljMGWm22VyLmvLZEqBMPUNjf6FNZrmMDUBTlEsFxk88_kOCQ=w120-h120-l90-rw?host=lh3.googleusercontent.com",
      "uploaderName": "Queen",
      "uploaderUrl": "/channel/UCEPMVbUzImPl4p8k4LkGevA",
      "uploaderAvatar": null,
      "uploadedDate": null,
      "shortDescription": null,
      "duration": 218,
      "views": -1,
      "uploaded": -1,
      "uploaderVerified": false
    },
    {
      "url": "/watch?v=hBp4dgE7Bho",
      "title": "Don't Stop Me Now (...Revisited)",
      "thumbnail": "https://pipedproxy.kavin.rocks/jRsNoO2SWEPNj9YpAAK_TpUx4izOiAl1XUBWwFDSNosxGj7c8SfsRYtL0n_5QOsGEEhjLG_01Pp-T9g=w120-h120-l90-rw?host=lh3.googleusercontent.com",
      "uploaderName": "Queen",
      "uploaderUrl": "/channel/UCEPMVbUzImPl4p8k4LkGevA",
      "uploaderAvatar": null,
      "uploadedDate": null,
      "shortDescription": null,
      "duration": 218,
      "views": -1,
      "uploaded": -1,
      "uploaderVerified": false
    },
    {
      "url": "/watch?v=yl3TsqL0ZPw",
      "title": "Bohemian Rhapsody",
      "thumbnail": "https://pipedproxy.kavin.rocks/jRsNoO2SWEPNj9YpAAK_TpUx4izOiAl1XUBWwFDSNosxGj7c8SfsRYtL0n_5QOsGEEhjLG_01Pp-T9g=w120-h120-l90-rw?host=lh3.googleusercontent.com",
      "uploaderName": "Queen",
      "uploaderUrl": "/channel/UCEPMVbUzImPl4p8k4LkGevA",
      "uploaderAvatar": null,
      "uploadedDate": null,
      "shortDescription": null,
      "duration": 355,
      "views": -1,
      "uploaded": -1,
      "uploaderVerified": false
    },
    {
      "url": "/watch?v=x8hUwP_5Qc4",
      "title": "Somebody To Love",
      "thumbnail": "https://pipedproxy.kavin.rocks/iSp4bKNyFnhc63fM6J5DQLxJ35Jip-mnXfMx9nns1bbqCvRZoGQYWMtFRadASJo23NLHiA_ZcW-AoDB-qw=w120-h120-l90-rw?host=lh3.googleusercontent.com",
      "uploaderName": "Queen",
      "uploaderUrl": "/channel/UCEPMVbUzImPl4p8k4LkGevA",
      "uploaderAvatar": null,
      "uploadedDate": null,
      "shortDescription": null,
      "duration": 297,
      "views": -1,
      "uploaded": -1,
      "uploaderVerified": false
    },
    {
      "url": "/watch?v=yvQYV520tS8",
      "title": "Bohemian Rhapsody (Live Aid)",
      "thumbnail": "https://pipedproxy.kavin.rocks/jRsNoO2SWEPNj9YpAAK_TpUx4izOiAl1XUBWwFDSNosxGj7c8SfsRYtL0n_5QOsGEEhjLG_01Pp-T9g=w120-h120-l90-rw?host=lh3.googleusercontent.com",
      "uploaderName": "Queen",
      "uploaderUrl": "/channel/UCEPMVbUzImPl4p8k4LkGevA",
      "uploaderAvatar": null,
      "uploadedDate": null,
      "shortDescription": null,
      "duration": 148,
      "views": -1,
      "uploaded": -1,
      "uploaderVerified": false
    },
    {
      "url": "/watch?v=OTKjISlQOhs",
      "title": "Who Wants To Live Forever",
      "thumbnail": "https://pipedproxy.kavin.rocks/kBrnnQZxMq9G4VCownBnQB3nmi0LrolZAG0a2c0-9Bt8BAFHPDafdQYdbZUJlaqVM1vjC3GWLJ3W1dtb=w120-h120-l90-rw?host=lh3.googleusercontent.com",
      "uploaderName": "Queen",
      "uploaderUrl": "/channel/UCEPMVbUzImPl4p8k4LkGevA",
      "uploaderAvatar": null,
      "uploadedDate": null,
      "shortDescription": null,
      "duration": 296,
      "views": -1,
      "uploaded": -1,
      "uploaderVerified": false
    },
    {
      "url": "/watch?v=yPtMiS-Pa6U",
      "title": "Too Much Love Will Kill You",
      "thumbnail": "https://pipedproxy.kavin.rocks/UDUEnGzl4fNihU0EBivl78zuXHg9QJ3NfRxWP-Wm_7qKIc8l3LjvvO6DOlYelWVbo0yFZHNq9tcc3CwCqA=w120-h120-l90-rw?host=lh3.googleusercontent.com",
      "uploaderName": "Queen",
      "uploaderUrl": "/channel/UCEPMVbUzImPl4p8k4LkGevA",
      "uploaderAvatar": null,
      "uploadedDate": null,
      "shortDescription": null,
      "duration": 260,
      "views": -1,
      "uploaded": -1,
      "uploaderVerified": false
    },
    {
      "url": "/watch?v=bR-gZQLO26w",
      "title": "Killer Queen",
      "thumbnail": "https://pipedproxy.kavin.rocks/GL-w-E92hiYGUyM3gGOa4LNy7T0rozrmalb0QAd38qmWjJw0cogJzihK7FUHYLzlgiyCFA_stQsy2xyAyA=w120-h120-l90-rw?host=lh3.googleusercontent.com",
      "uploaderName": "Queen",
      "uploaderUrl": "/channel/UCEPMVbUzImPl4p8k4LkGevA",
      "uploaderAvatar": null,
      "uploadedDate": null,
      "shortDescription": null,
      "duration": 180,
      "views": -1,
      "uploaded": -1,
      "uploaderVerified": false
    },
    {
      "url": "/watch?v=RJo21ubguDE",
      "title": "I Want It All",
      "thumbnail": "https://pipedproxy.kavin.rocks/kBrnnQZxMq9G4VCownBnQB3nmi0LrolZAG0a2c0-9Bt8BAFHPDafdQYdbZUJlaqVM1vjC3GWLJ3W1dtb=w120-h120-l90-rw?host=lh3.googleusercontent.com",
      "uploaderName": "Queen",
      "uploaderUrl": "/channel/UCEPMVbUzImPl4p8k4LkGevA",
      "uploaderAvatar": null,
      "uploadedDate": null,
      "shortDescription": null,
      "duration": 242,
      "views": -1,
      "uploaded": -1,
      "uploaderVerified": false
    },
    {
      "url": "/watch?v=YkLLcIKhJ64",
      "title": "Dancing Queen",
      "thumbnail": "https://pipedproxy.kavin.rocks/uwZJDAz4hZnM_CYZS3Lgcibm1UFShAVDQqqCN4wZytyZAbFPqk-bB4MvIahp4Egszu0ulGncj459bB0b=w120-h120-l90-rw?host=lh3.googleusercontent.com",
      "uploaderName": "ABBA",
      "uploaderUrl": "/channel/UCuubAXN9AYgtcmSrD0frggQ",
      "uploaderAvatar": null,
      "uploadedDate": null,
      "shortDescription": null,
      "duration": 231,
      "views": -1,
      "uploaded": -1,
      "uploaderVerified": false
    },
    {
      "url": "/watch?v=WwrVNc5Ce78",
      "title": "Queen",
      "thumbnail": "https://pipedproxy.kavin.rocks/8_IBBL_6SDMpHTXujAEe1DseBh2-_optfFMGWGpuWW7YXoA1gQbb5FLxfyFQ98cDn78-p7ojK6UXaY0=w120-h120-l90-rw?host=lh3.googleusercontent.com",
      "uploaderName": "Marta Daddato",
      "uploaderUrl": "/channel/UCtyprPdms2eat9lzI-y1iag",
      "uploaderAvatar": null,
      "uploadedDate": null,
      "shortDescription": null,
      "duration": 157,
      "views": -1,
      "uploaded": -1,
      "uploaderVerified": false
    },
    {
      "url": "/watch?v=N2qk6VZokx0",
      "title": "Good Old-Fashioned Lover Boy",
      "thumbnail": "https://pipedproxy.kavin.rocks/iSp4bKNyFnhc63fM6J5DQLxJ35Jip-mnXfMx9nns1bbqCvRZoGQYWMtFRadASJo23NLHiA_ZcW-AoDB-qw=w120-h120-l90-rw?host=lh3.googleusercontent.com",
      "uploaderName": "Queen",
      "uploaderUrl": "/channel/UCEPMVbUzImPl4p8k4LkGevA",
      "uploaderAvatar": null,
      "uploadedDate": null,
      "shortDescription": null,
      "duration": 174,
      "views": -1,
      "uploaded": -1,
      "uploaderVerified": false
    },
    {
      "url": "/watch?v=2yzkYTPe710",
      "title": "Queen",
      "thumbnail": "https://pipedproxy.kavin.rocks/aa_jm3KAqjkKfzXrLF02WQiRNK7oAq4lahzw3Daq-mrZT5lJ_GkWR1x18VJiTH4ZepvsUJDAdmDmexI=w120-h120-l90-rw?host=lh3.googleusercontent.com",
      "uploaderName": "Jacuś",
      "uploaderUrl": "/channel/UCvlEe5thcYBgY6D3fapCrWQ",
      "uploaderAvatar": null,
      "uploadedDate": null,
      "shortDescription": null,
      "duration": 197,
      "views": -1,
      "uploaded": -1,
      "uploaderVerified": false
    },
    {
      "url": "/watch?v=S0UEr1lMCXA",
      "title": "Queen of Hearts",
      "thumbnail": "https://pipedproxy.kavin.rocks/9GQPTK7-tVUpqNz2gHNQ8HsoXiVGsXlAp0saq9VlDRJoK6QSArzPqQT-WnYWSIroj53nk-ipYKSY9U_-eA=w120-h120-l90-rw?host=lh3.googleusercontent.com",
      "uploaderName": "Bad Boys Blue",
      "uploaderUrl": "/channel/UCyfrr4gGevRfLcd7J5dnG2w",
      "uploaderAvatar": null,
      "uploadedDate": null,
      "shortDescription": null,
      "duration": 251,
      "views": -1,
      "uploaded": -1,
      "uploaderVerified": false
    },
    {
      "url": "/watch?v=Rix3hoKJoMA",
      "title": "Made In Heaven",
      "thumbnail": "https://pipedproxy.kavin.rocks/UDUEnGzl4fNihU0EBivl78zuXHg9QJ3NfRxWP-Wm_7qKIc8l3LjvvO6DOlYelWVbo0yFZHNq9tcc3CwCqA=w120-h120-l90-rw?host=lh3.googleusercontent.com",
      "uploaderName": "Queen",
      "uploaderUrl": "/channel/UCEPMVbUzImPl4p8k4LkGevA",
      "uploaderAvatar": null,
      "uploadedDate": null,
      "shortDescription": null,
      "duration": 325,
      "views": -1,
      "uploaded": -1,
      "uploaderVerified": false
    },
    {
      "url": "/watch?v=rwPSw-sgxjY",
      "title": "These Are The Days Of Our Lives",
      "thumbnail": "https://pipedproxy.kavin.rocks/yrA5W5AsYMjH0xUboqxxPc3NJ7GgUJqyT7JeepRlygNp-E-34I1lRplzP1E3woBPZf3TEsA3HpUuAi8T=w120-h120-l90-rw?host=lh3.googleusercontent.com",
      "uploaderName": "Queen",
      "uploaderUrl": "/channel/UCEPMVbUzImPl4p8k4LkGevA",
      "uploaderAvatar": null,
      "uploadedDate": null,
      "shortDescription": null,
      "duration": 263,
      "views": -1,
      "uploaded": -1,
      "uploaderVerified": false
    },
    {
      "url": "/watch?v=Ipp6Hsp0L4c",
      "title": "Princes Of The Universe",
      "thumbnail": "https://pipedproxy.kavin.rocks/VQIR5tVrXTMPy9G7Ds_PWtremaKHbJY-qQtWumL_YLHCKGifwkXgLepnfcXOG_AGSvaRCBaPvVrNtsp9fQ=w120-h120-s-l90-rw?host=lh3.googleusercontent.com",
      "uploaderName": "Queen",
      "uploaderUrl": "/channel/UCEPMVbUzImPl4p8k4LkGevA",
      "uploaderAvatar": null,
      "uploadedDate": null,
      "shortDescription": null,
      "duration": 214,
      "views": -1,
      "uploaded": -1,
      "uploaderVerified": false
    }
  ],
  "nextpage": "{\"url\":\"https://music.youtube.com/youtubei/v1/search?ctoken=EqwDEgVxdWVlbhqiA0VnLUtBUXdJQVJBQUdBQWdBQ2dBTUFCSUZHb0tFQVFRQlJBREVBb1FDWUlCQzNkSmNXRTVkVlp1V0VOUmdnRUxNMDh3UkRaTmRsZEdaalNDQVFzNGNqTkdZVU5wVmtaaVFZSUJDekppY1cwMFoxSlpNMjFCZ2dFTGFFSndOR1JuUlRkQ2FHLUNBUXQ1YkROVWMzRk1NRnBRZDRJQkMzZzRhRlYzVUY4MVVXTTBnZ0VMZVhaUldWWTFNakIwVXppQ0FRdFBWRXRxU1ZOc1VVOW9jNElCQzNsUWRFMXBVeTFRWVRaVmdnRUxZbEl0WjFwUlRFOHlObmVDQVF0U1NtOHlNWFZpWjNWRVJZSUJDMWxyVEV4alNVdG9TalkwZ2dFTFYzZHlWazVqTlVObE56aUNBUXRPTW5Gck5sWmFiMnQ0TUlJQkN6SjVlbXRaVkZCbE56RXdnZ0VMVXpCVlJYSXhiRTFEV0VHQ0FRdFNhWGd6YUc5TFNtOU5RWUlCQzNKM1VGTjNMWE5uZUdwWmdnRUxTWEJ3TmtoemNEQk1OR00lM0QY8erQLg%3D%3D&continuation=EqwDEgVxdWVlbhqiA0VnLUtBUXdJQVJBQUdBQWdBQ2dBTUFCSUZHb0tFQVFRQlJBREVBb1FDWUlCQzNkSmNXRTVkVlp1V0VOUmdnRUxNMDh3UkRaTmRsZEdaalNDQVFzNGNqTkdZVU5wVmtaaVFZSUJDekppY1cwMFoxSlpNMjFCZ2dFTGFFSndOR1JuUlRkQ2FHLUNBUXQ1YkROVWMzRk1NRnBRZDRJQkMzZzRhRlYzVUY4MVVXTTBnZ0VMZVhaUldWWTFNakIwVXppQ0FRdFBWRXRxU1ZOc1VVOW9jNElCQzNsUWRFMXBVeTFRWVRaVmdnRUxZbEl0WjFwUlRFOHlObmVDQVF0U1NtOHlNWFZpWjNWRVJZSUJDMWxyVEV4alNVdG9TalkwZ2dFTFYzZHlWazVqTlVObE56aUNBUXRPTW5Gck5sWmFiMnQ0TUlJQkN6SjVlbXRaVkZCbE56RXdnZ0VMVXpCVlJYSXhiRTFEV0VHQ0FRdFNhWGd6YUc5TFNtOU5RWUlCQzNKM1VGTjNMWE5uZUdwWmdnRUxTWEJ3TmtoemNEQk1OR00lM0QY8erQLg%3D%3D&alt=json&key=AIzaSyC9XL3ZjWddXya6X74dJoCTL-WEYFDNX30\",\"id\":null,\"ids\":null,\"cookies\":null,\"body\":null}",
  "suggestion": "",
  "corrected": false
}
